{
  "id": "08-density",
  "title": "Плотность, масса и геометрический объём",
  "purpose": "Как масса единицы объёма связывает геометрию и физику.",
  "sections": [
    {
      "type": "intro",
      "title": "Плотность, масса и геометрический объём",
      "lead": "Введение в тему, её практический смысл и маршрут изучения.",
      "purpose": "Как масса единицы объёма связывает геометрию и физику.",
      "prereq": "объём и умножение"
    },
    {
      "type": "content",
      "label": "Наблюдение",
      "title": "С чего начинается идея",
      "html": "<div class=\"card observe\"><p>Одинаковые объёмы разных материалов могут иметь разную массу.</p></div><div class=\"note\">Сначала объяснение словами и рисунком. Обозначения и формулы появятся позже.</div>"
    },
    {
      "type": "steps",
      "title": "От наблюдения к правилу",
      "items": [
        "Назови две или больше измеряемых величины.",
        "Укажи единицы измерения.",
        "Опиши связь полноценным предложением.",
        "Проверь правило на простом примере.",
        "Введи короткие буквенные обозначения.",
        "Запиши формулу и укажи условия, при которых она работает."
      ],
      "note": "Буквы являются сокращениями названий величин, а не самостоятельными объектами без смысла."
    },
    {
      "type": "demo",
      "title": "Интерактивное исследование",
      "text": "Изменяй параметры и формулируй наблюдения своими словами.",
      "demo": "area"
    },
    {
      "type": "tasks",
      "title": "Задачи от ситуации к записи"
    },
    {
      "type": "factory",
      "title": "Фабрика новых задач"
    },
    {
      "type": "content",
      "label": "Обратный процесс",
      "title": "От формулы к жизненной ситуации",
      "html": "<div class=\"card idea\"><p>Для закрепления выбери готовую формулу и придумай минимум один реальный или геометрический смысл. Назови величины, единицы и ограничения модели.</p></div>"
    },
    {
      "type": "summary",
      "title": "Что должно остаться после урока",
      "items": [
        "Я понимаю, от какого наблюдения появилась зависимость.",
        "Я могу описать правило без букв.",
        "Я могу ввести обозначения и объяснить каждую букву.",
        "Я могу проверить единицы и условия применимости.",
        "Я могу решить прямую задачу и придумать ситуацию по формуле."
      ]
    }
  ],
  "tasks": [
    {
      "title": "Деталь",
      "q": "Плотность 3 г/см³, объём 8 см³. Найди массу.",
      "hint": "Масса одного кубического сантиметра умножается на число кубиков.",
      "solution": "m=3·8=24 г.",
      "answer": 24,
      "level": "Базовое"
    },
    {
      "title": "Куб",
      "q": "Куб с ребром 3 см изготовлен из материала плотностью 4 г/см³. Найди массу.",
      "hint": "Сначала V=3³.",
      "solution": "V=27 см³, m=4·27=108 г.",
      "answer": 108,
      "level": "Среднее"
    },
    {
      "title": "Функция высоты",
      "q": "Составь массу цилиндра как функцию высоты при постоянных r и ρ.",
      "hint": "V=πr²h, затем m=ρV.",
      "solution": "m(h)=ρπr²h, линейная функция высоты.",
      "answer": null,
      "level": "Продвинутое"
    }
  ],
  "factory": [
    "density",
    "volume"
  ]
}